ansibug/__init__.py
ansibug/__main__.py
ansibug/_debug_adapter.py
ansibug/_debuggee.py
ansibug/_exec_playbook.py
ansibug/_logging.py
ansibug/_mp_queue.py
ansibug/_singleton.py
ansibug/_socket_helper.py
ansibug/_tls.py
ansibug/_version.py
ansibug/py.typed
ansibug/ansible_collections/ansibug/dap/plugins/callback/debug.py
ansibug/ansible_collections/ansibug/dap/plugins/plugin_utils/_breakpoints.py
ansibug/ansible_collections/ansibug/dap/plugins/plugin_utils/_repl_util.py
ansibug/ansible_collections/ansibug/dap/plugins/plugin_utils/_variables.py
ansibug/ansible_collections/ansibug/dap/plugins/strategy/debug.py
ansibug/dap/__init__.py
ansibug/dap/_adapter.py
ansibug/dap/_events.py
ansibug/dap/_messages.py
ansibug/dap/_requests.py
ansibug/dap/_responses.py
ansibug/dap/_types.py
ansibug-0.3.1.dist-info/licenses/LICENSE
ansibug-0.3.1.dist-info/METADATA
ansibug-0.3.1.dist-info/WHEEL
ansibug-0.3.1.dist-info/top_level.txt
ansibug-0.3.1.dist-info/RECORD
