Metadata-Version: 2.4
Name: ansibug
Version: 0.3.1
Summary: Ansible Debug Adapter Protocol Implementation
Author-email: Jordan Borean <jborean93@gmail.com>
License-Expression: MIT
Project-URL: homepage, https://github.com/jborean93/ansibug
Keywords: ansible,debug,lsp,dap
Classifier: Development Status :: 4 - Beta
Classifier: Programming Language :: Python :: 3
Classifier: Programming Language :: Python :: 3.10
Classifier: Programming Language :: Python :: 3.11
Classifier: Programming Language :: Python :: 3.12
Classifier: Programming Language :: Python :: 3.13
Requires-Python: >=3.10
License-File: LICENSE
Provides-Extra: dev
Requires-Dist: ansible-core>=2.16.0; extra == "dev"
Requires-Dist: argcomplete; extra == "dev"
Requires-Dist: coverage[toml]>=5.3; extra == "dev"
Requires-Dist: cryptography; extra == "dev"
Requires-Dist: black==24.10.0; extra == "dev"
Requires-Dist: isort==5.13.2; extra == "dev"
Requires-Dist: mypy==1.13.0; extra == "dev"
Requires-Dist: pre-commit; extra == "dev"
Requires-Dist: pytest; extra == "dev"
Requires-Dist: pytest-timeout; extra == "dev"
Requires-Dist: pytest-xdist; extra == "dev"
Requires-Dist: tox>=4.0.0; extra == "dev"
Dynamic: license-file
